visualgl/__init__.py
visualgl/application.py
visualgl/bindings.py
visualgl/camera/__init__.py
visualgl/camera/camera.py
visualgl/camera/camera_controller.py
visualgl/camera/camera_controller_parameters.py
visualgl/camera/exceptions.py
visualgl/camera/projection.py
visualgl/controller.py
visualgl/exceptions.py
visualgl/filetypes/stl/stl_parser.py
visualgl/filetypes/stl/stl_type.py
visualgl/filetypes/stl/stl_writer.py
visualgl/opengl/__init__.py
visualgl/opengl/buffer.py
visualgl/opengl/decorators.py
visualgl/opengl/exceptions.py
visualgl/opengl/shader.py
visualgl/opengl/shader_program.py
visualgl/opengl/uniform.py
visualgl/opengl/uniform_buffer.py
visualgl/renderer.py
visualgl/scene/__init__.py
visualgl/scene/ambient_light.py
visualgl/scene/scene.py
visualgl/settings.py
visualgl/timer.py
visualgl/utils.py
visualgl/window/__init__.py
visualgl/window/exceptions.py
visualgl/window/input_event.py
visualgl/window/input_handler.py
visualgl/window/layout.py
visualgl/window/layouts/grid.py
visualgl/window/viewport.py
visualgl/window/viewports/scene_viewport.py
visualgl/window/window.py
visualgl-0.0.2.dist-info/LICENSE
visualgl-0.0.2.dist-info/WHEEL
visualgl-0.0.2.dist-info/METADATA
visualgl-0.0.2.dist-info/RECORD
